{
  "generated_at": "2026-04-01 11:33:58",
  "csv_path": "/home/runner/work/stock-screener/stock-screener/results/backtest_20251222_20260325_20260401_113358.csv",
  "n_signals": 5047,
  "n_valid": 5047,
  "n_dates": 61,
  "n_tickers": 375,
  "hit_threshold_pct": 3.0,
  "avg_ret_1d": 0.047,
  "win_rate_1d": 51.2,
  "hit_rate_1d": 23.1,
  "hit_rates_by_day": {
    "1d": 23.1,
    "2d": 36.4,
    "3d": 44.5,
    "4d": 50.2,
    "5d": 54.7
  },
  "ret_stats_by_day": {
    "ret_1d": {
      "mean": 0.047,
      "median": 0.086,
      "win_rate": 51.2,
      "max": 29.499,
      "min": -25.237
    },
    "ret_2d": {
      "mean": 0.106,
      "median": 0.089,
      "win_rate": 51.4,
      "max": 29.499,
      "min": -25.237
    },
    "ret_3d": {
      "mean": 0.11,
      "median": 0.105,
      "win_rate": 51.6,
      "max": 29.499,
      "min": -25.237
    },
    "ret_4d": {
      "mean": 0.062,
      "median": 0.058,
      "win_rate": 50.7,
      "max": 29.499,
      "min": -25.237
    },
    "ret_5d": {
      "mean": 0.145,
      "median": 0.117,
      "win_rate": 51.8,
      "max": 34.722,
      "min": -25.237
    }
  },
  "top_tickers": [
    {
      "ticker": 3103,
      "name": "ユニチカ",
      "hit_count": 38,
      "avg_ret": 7.081,
      "signal_count": 38
    },
    {
      "ticker": 4004,
      "name": "レゾナック・ホールディングス",
      "hit_count": 26,
      "avg_ret": 3.944,
      "signal_count": 26
    },
    {
      "ticker": 3110,
      "name": "日東紡績",
      "hit_count": 24,
      "avg_ret": 4.442,
      "signal_count": 24
    },
    {
      "ticker": 1514,
      "name": "住石ホールディングス",
      "hit_count": 24,
      "avg_ret": 4.326,
      "signal_count": 24
    },
    {
      "ticker": 4107,
      "name": "伊勢化学工業",
      "hit_count": 24,
      "avg_ret": 4.373,
      "signal_count": 24
    },
    {
      "ticker": 1662,
      "name": "石油資源開発",
      "hit_count": 23,
      "avg_ret": 4.228,
      "signal_count": 23
    },
    {
      "ticker": 1515,
      "name": "日鉄鉱業",
      "hit_count": 22,
      "avg_ret": 3.796,
      "signal_count": 22
    },
    {
      "ticker": 3997,
      "name": "トレードワークス",
      "hit_count": 19,
      "avg_ret": 2.77,
      "signal_count": 19
    },
    {
      "ticker": 4062,
      "name": "イビデン",
      "hit_count": 17,
      "avg_ret": 3.907,
      "signal_count": 17
    },
    {
      "ticker": 1605,
      "name": "ＩＮＰＥＸ",
      "hit_count": 16,
      "avg_ret": 3.525,
      "signal_count": 16
    },
    {
      "ticker": 2160,
      "name": "ジーエヌアイグループ",
      "hit_count": 15,
      "avg_ret": 3.42,
      "signal_count": 15
    },
    {
      "ticker": 4182,
      "name": "三菱瓦斯化学",
      "hit_count": 15,
      "avg_ret": 5.131,
      "signal_count": 15
    },
    {
      "ticker": 4082,
      "name": "第一稀元素化学工業",
      "hit_count": 15,
      "avg_ret": 6.538,
      "signal_count": 15
    },
    {
      "ticker": 4022,
      "name": "ラサ工業",
      "hit_count": 15,
      "avg_ret": 4.314,
      "signal_count": 15
    },
    {
      "ticker": 3315,
      "name": "日本コークス工業",
      "hit_count": 14,
      "avg_ret": 2.734,
      "signal_count": 14
    },
    {
      "ticker": 2768,
      "name": "双日",
      "hit_count": 14,
      "avg_ret": 2.918,
      "signal_count": 14
    },
    {
      "ticker": 1885,
      "name": "東亜建設工業",
      "hit_count": 14,
      "avg_ret": 4.227,
      "signal_count": 14
    },
    {
      "ticker": 1963,
      "name": "日揮ホールディングス",
      "hit_count": 14,
      "avg_ret": 3.108,
      "signal_count": 14
    },
    {
      "ticker": 4063,
      "name": "信越化学工業",
      "hit_count": 14,
      "avg_ret": 3.456,
      "signal_count": 14
    },
    {
      "ticker": 3444,
      "name": "菊池製作所",
      "hit_count": 13,
      "avg_ret": 4.856,
      "signal_count": 13
    }
  ]
}